skin.py
skin-0.0.7.dist-info/METADATA
skin-0.0.7.dist-info/RECORD
skin-0.0.7.dist-info/WHEEL
skin-0.0.7.dist-info/top_level.txt
