Metadata-Version: 1.2
Name: skin
Version: 0.0.7
Summary: Getitem-objects «skin» for attribute-like access
Home-page: https://github.com/pohmelie/skin
Author: pohmelie
Author-email: multisosnooley@gmail.com
License: Apache 2
Platform: UNKNOWN
Classifier: Development Status :: 3 - Alpha
Classifier: Intended Audience :: Developers
Classifier: Programming Language :: Python :: 3
Requires-Python: >= 3.4
